{
    "actions": [],
    "autoname": "autoincrement",
    "creation": "2024-12-09 17:00:00.000000",
    "doctype": "DocType",
    "editable_grid": 1,
    "engine": "InnoDB",
    "field_order": [
        "emoji",
        "user"
    ],
    "fields": [
        {
            "fieldname": "emoji",
            "fieldtype": "Data",
            "in_list_view": 1,
            "label": "Emoji",
            "reqd": 1
        },
        {
            "fieldname": "user",
            "fieldtype": "Data",
            "in_list_view": 1,
            "label": "User",
            "read_only": 1
        }
    ],
    "index_web_pages_for_search": 1,
    "istable": 1,
    "links": [],
    "modified": "2024-12-09 17:00:00.000000",
    "modified_by": "Administrator",
    "module": "Helpdesk",
    "name": "HD Reaction",
    "naming_rule": "Autoincrement",
    "owner": "Administrator",
    "permissions": [],
    "sort_field": "modified",
    "sort_order": "DESC",
    "states": []
}